richclass/__init__.py
richclass/src/__init__.py
richclass/src/richpath.py
richclass/tests/__init__.py
richclass/tests/monitoring_documents.py
richclass-1.0.1.dist-info/LICENSE
richclass-1.0.1.dist-info/METADATA
richclass-1.0.1.dist-info/WHEEL
richclass-1.0.1.dist-info/top_level.txt
richclass-1.0.1.dist-info/RECORD
