Metadata-Version: 2.1
Name: richclass
Version: 1.0.1
Summary: A collection of feature rich classes
Home-page: https://github.com/UpAllNate/richclass
Author: UpAllNate
Author-email: upallnate@gmail.com
License: MIT
Keywords: class,features,tutorial
Classifier: License :: OSI Approved :: MIT License
Classifier: Programming Language :: Python
Classifier: Programming Language :: Python :: 3
License-File: LICENSE
Provides-Extra: dev
Requires-Dist: twine >=4.0.2 ; extra == 'dev'
